garpix_keycloak/CHANGELOG.md
garpix_keycloak/CONTRIBUTING.md
garpix_keycloak/MANIFEST.in
garpix_keycloak/README.md
garpix_keycloak/__init__.py
garpix_keycloak/apps.py
garpix_keycloak/backends.py
garpix_keycloak/middlewares.py
garpix_keycloak/mixins.py
garpix_keycloak/services.py
garpix_keycloak/setup.py
garpix_keycloak/__pycache__/__init__.cpython-310.pyc
garpix_keycloak/__pycache__/apps.cpython-310.pyc
garpix_keycloak/__pycache__/middlewares.cpython-310.pyc
garpix_keycloak/__pycache__/mixins.cpython-310.pyc
garpix_keycloak/__pycache__/services.cpython-310.pyc
garpix_keycloak-1.2.1.dist-info/METADATA
garpix_keycloak-1.2.1.dist-info/WHEEL
garpix_keycloak-1.2.1.dist-info/top_level.txt
garpix_keycloak-1.2.1.dist-info/RECORD
