Metadata-Version: 2.1
Name: garpix-keycloak
Version: 1.2.1
Home-page: https://github.com/garpixcms/garpix_keycloak
Author: Garpix LTD
Author-email: info@garpix.com
License: MIT
Classifier: Development Status :: 4 - Beta
Classifier: Environment :: Web Environment
Classifier: Intended Audience :: Developers
Classifier: License :: OSI Approved :: MIT License
Classifier: Operating System :: OS Independent
Classifier: Programming Language :: Python
Classifier: Framework :: Django
Classifier: Programming Language :: Python :: 3.8
Requires-Dist: Django (<4,>=3.1)
Requires-Dist: djangorestframework (>=3.8)
Requires-Dist: django-rest-framework-social-oauth2 (>=1.1.0)
Requires-Dist: garpix-utils (>=1.8.0)
